galxiai/__init__.py
galxiai/clasreq.py
galxiai/const.py
galxiai/payload.py
galxiai/ql.py
galxiai/req.py
galxiai/reqbase.py
galxiai/sqlite_galxi.py
galxiai/ut.py
galxiai/xxcl.py
galxiai-0.50.9.dist-info/LICENSE
galxiai-0.50.9.dist-info/METADATA
galxiai-0.50.9.dist-info/WHEEL
galxiai-0.50.9.dist-info/top_level.txt
galxiai-0.50.9.dist-info/RECORD
